{
	"stefan" :
	{
		"class" : "cthbishop",
		"female" : false,
		"images" :
		{
			"specialtySmall" : "cathedral/heroes/stefan/spec-small.bmp",
			"specialtyLarge" : "cathedral/heroes/stefan/spec-large.bmp",
			"large" : "cathedral/heroes/stefan/portrait-large.bmp",
			"small" : "cathedral/heroes/stefan/portrait-small.bmp"
		},

		"army" :
		[
			{ "creature" : "cthAttackDog", "min" : 9, "max" : 15 },
			{ "creature" : "cthSlayer", "min" :  6, "max" :  9 },
			{ "creature" : "cthWitchHunter", "min" :  3, "max" :  6 }
		],

		"skills" :
		[
			{
				"level" : "basic",
				"skill" : "intelligence"
			},
			{
				"level" : "basic",
				"skill" : "wisdom"
			}
		],
		"texts" :
		{
			"name" : "Franco J",
			"biography" : "Franco J was the city's bishop and saved many people when disaster struck. But now he believes punishment is more effective than redemption. He believes that the disaster of that year could have been God's punishment for the blasphemers. Therefore, he is determined to protect the rebuilt Church and will no longer show mercy to anyone he deems sinful.",
			"specialty" :
			{
				"description" : "Receives a 5% per level bonus to Intelligence skill.",
				"tooltip" : "Intelligence Bonus",
				"name" : "Intelligence"
			}
		},
		"spellbook" :
		[
			"stoneSkin"
		],
		"specialty" : {
			"bonuses" : {
				"resistance" : {
					"targetSourceType" : "SECONDARY_SKILL",
					"type" : "MANA_PER_KNOWLEDGE_PERCENTAGE",
					"val" : 5,
					"valueType" : "PERCENT_TO_TARGET_TYPE",
					"updater" : "TIMES_HERO_LEVEL"
				}
			}
		}		
	}
}
